hypersync_fuel-0.1.2.dist-info/METADATA
hypersync_fuel-0.1.2.dist-info/WHEEL
hypersync_fuel-0.1.2.dist-info/license_files/LICENSE
hypersync_fuel/__init__.py
hypersync_fuel/hypersync_fuel.cp311-win32.pyd
hypersync_fuel-0.1.2.dist-info/RECORD
