Metadata-Version: 2.3
Name: hypersync-fuel
Version: 0.1.2
Classifier: Programming Language :: Rust
Classifier: Programming Language :: Python :: Implementation :: CPython
Classifier: Programming Language :: Python :: Implementation :: PyPy
Classifier: Development Status :: 3 - Alpha
Classifier: Topic :: Database :: Front-Ends
Classifier: Topic :: Software Development :: Libraries
Requires-Dist: strenum >=0.4.15, <0.4.16
License-File: LICENSE
Requires-Python: >=3.9
